wurfapi/__init__.py
wurfapi/__main__.py
wurfapi/check_api_schema.py
wurfapi/check_output.py
wurfapi/collapse_inline_namespaces.py
wurfapi/compat.py
wurfapi/doxygen_downloader.py
wurfapi/doxygen_error.py
wurfapi/doxygen_generator.py
wurfapi/doxygen_parser.py
wurfapi/link_mapper.py
wurfapi/link_provider.py
wurfapi/location_mapper.py
wurfapi/run.py
wurfapi/run_error.py
wurfapi/run_result.py
wurfapi/template_render.py
wurfapi/wurfapi_directive.py
wurfapi/wurfapi_error.py
wurfapi/template_files/class_synopsis.rst
wurfapi/template_files/defines_synopsis.rst
wurfapi/template_files/enum_synopsis.rst
wurfapi/template_files/function_synopsis.rst
wurfapi/template_files/macros.rst
wurfapi/template_files/namespace_synopsis.rst
wurfapi/template_files/type_alias_synopsis.rst
wurfapi-9.1.1.dist-info/METADATA
wurfapi-9.1.1.dist-info/WHEEL
wurfapi-9.1.1.dist-info/entry_points.txt
wurfapi-9.1.1.dist-info/top_level.txt
wurfapi-9.1.1.dist-info/RECORD
